[
    {
        "product_id":"56834",
        "general_id":"elise_56834",
        "sku":"FS2312086DIWOWH",
        "product_name":"ĐẦM SUÔNG TRẮNG TAY TƠ THÊU HOA NGỰC",
        "price":"2.098.000 VND",
        "size":[
            "S",
            "M",
            "L"
        ],
        "color":null,
        "description":null,
        "image_list":{
            "001_ĐẦM SUÔNG TRẮNG TAY TƠ THÊU HOA NGỰC":"https:\/\/elise.vn\/media\/catalog\/product\/cache\/bb52e54e5ec1828d48ae8bf7c98f9f69\/f\/s\/fs2312086diwowh1.jpg",
            "002_ĐẦM SUÔNG TRẮNG TAY TƠ THÊU HOA NGỰC":"https:\/\/elise.vn\/media\/catalog\/product\/cache\/bb52e54e5ec1828d48ae8bf7c98f9f69\/f\/s\/fs2312086diwowh3.jpg",
            "003_ĐẦM SUÔNG TRẮNG TAY TƠ THÊU HOA NGỰC":"https:\/\/elise.vn\/media\/catalog\/product\/cache\/bb52e54e5ec1828d48ae8bf7c98f9f69\/f\/s\/fs2312086diwowh2.jpg",
            "004_ĐẦM SUÔNG TRẮNG TAY TƠ THÊU HOA NGỰC":"https:\/\/elise.vn\/media\/catalog\/product\/cache\/bb52e54e5ec1828d48ae8bf7c98f9f69\/f\/s\/fs2312086diwowh.jpg"
        }
    }
]