[
    {
        "product_id":"56754",
        "general_id":"elise_56754",
        "sku":"FS2312038TNSIPP",
        "product_name":"SM LỤA HỒNG HT CỔ CHÉO DÂY XÍCH",
        "price":"998.000 VND",
        "size":[
            "S",
            "M",
            "L"
        ],
        "color":null,
        "description":null,
        "image_list":{
            "001_SM LỤA HỒNG HT CỔ CHÉO DÂY XÍCH":"https:\/\/elise.vn\/media\/catalog\/product\/cache\/bb52e54e5ec1828d48ae8bf7c98f9f69\/f\/s\/fs2312038tnsipp3.jpg",
            "002_SM LỤA HỒNG HT CỔ CHÉO DÂY XÍCH":"https:\/\/elise.vn\/media\/catalog\/product\/cache\/bb52e54e5ec1828d48ae8bf7c98f9f69\/f\/s\/fs2312038tnsipp_1.jpg",
            "003_SM LỤA HỒNG HT CỔ CHÉO DÂY XÍCH":"https:\/\/elise.vn\/media\/catalog\/product\/cache\/bb52e54e5ec1828d48ae8bf7c98f9f69\/f\/s\/fs2312038tnsipp2.jpg",
            "004_SM LỤA HỒNG HT CỔ CHÉO DÂY XÍCH":"https:\/\/elise.vn\/media\/catalog\/product\/cache\/bb52e54e5ec1828d48ae8bf7c98f9f69\/f\/s\/fs2312038tnsipp1_1.jpg"
        }
    }
]