[
    {
        "product_id":"56208",
        "general_id":"elise_56208",
        "sku":"FF2308171DIWOCR",
        "product_name":"ĐẦM KEM PHỐI TƠ ĐÍNH NƠ CỔ",
        "price":"2.098.000 VND",
        "size":[
            "S",
            "M",
            "L"
        ],
        "color":null,
        "description":null,
        "image_list":{
            "001_ĐẦM KEM PHỐI TƠ ĐÍNH NƠ CỔ":"https:\/\/elise.vn\/media\/catalog\/product\/cache\/bb52e54e5ec1828d48ae8bf7c98f9f69\/f\/f\/ff2308171diwocr.jpg",
            "002_ĐẦM KEM PHỐI TƠ ĐÍNH NƠ CỔ":"https:\/\/elise.vn\/media\/catalog\/product\/cache\/bb52e54e5ec1828d48ae8bf7c98f9f69\/f\/f\/ff2308171diwocr1.jpg",
            "003_ĐẦM KEM PHỐI TƠ ĐÍNH NƠ CỔ":"https:\/\/elise.vn\/media\/catalog\/product\/cache\/bb52e54e5ec1828d48ae8bf7c98f9f69\/f\/f\/ff2308171diwocr3.jpg",
            "004_ĐẦM KEM PHỐI TƠ ĐÍNH NƠ CỔ":"https:\/\/elise.vn\/media\/catalog\/product\/cache\/bb52e54e5ec1828d48ae8bf7c98f9f69\/f\/f\/ff2308171diwocr2.jpg"
        }
    }
]